open_list_queue.sv
/* verilator lint_off UNUSEDPARAM */
/* verilator lint_off UNUSEDSIGNAL */

`timescale 1ns / 1ps

module open_list_queue #(
    parameter QUEUE_SIZE = 4,  // Number of slots in each queue
    parameter DATA_WIDTH = 32,  // Data width for node f values
    parameter MAP_WIDTH = 16,  // Width of the map
    parameter MAP_HEIGHT = 16,  // Height of the map
    parameter MAX_F = 32'hFFFFFFFF  // Maximum value for f
) (
    input logic CLK,
    input logic RSTn,

    /* Input control signals */
    input logic i_wrt,  // enqueue
    input logic i_read,  // dequeue
    input logic i_valid,  // ready for next instruction
    // Node data inputs
    input logic [DATA_WIDTH-1:0] i_node_f,
    // input logic [ MAP_WIDTH-1:0] i_node_i,
    // input logic [MAP_HEIGHT-1:0] i_node_j,

    /* Output control signals */
    output logic o_ready_deq,  // read ready flag
    output logic o_ready_enq,  // write ready flag
    output logic o_ready_rep,  // replace ready flag
    output logic o_full,  // OB full
    output logic o_empty,  // OB empty
    output logic o_valid,  // OB[0] valid
    // Node data outputs
    output logic [DATA_WIDTH-1:0] o_node_f
    // output logic [ MAP_WIDTH-1:0] o_node_i,
    // output logic [MAP_HEIGHT-1:0] o_node_j
);

  localparam l_bits = $clog2(QUEUE_SIZE);

  logic [(l_bits+1):0] next_size, curr_size;

  logic [QUEUE_SIZE-1:0][DATA_WIDTH-1:0] inQueue, nextInQueue;
  logic [QUEUE_SIZE-1:0][DATA_WIDTH-1:0] outQueue, nextOutQueue;

  logic [QUEUE_SIZE-1:0] inQueueValid;
  logic [QUEUE_SIZE-1:0] nextInQueueValid;
  logic [QUEUE_SIZE-1:0] outQueueValid;
  logic [QUEUE_SIZE-1:0] nextOutQueueValid;

  logic [QUEUE_SIZE-1:0] lessThanPrevInQueue;
  logic [QUEUE_SIZE-1:0] lessThanNextInQueue;
  logic [QUEUE_SIZE-1:0] lessThanSameOutQueue;
  logic [QUEUE_SIZE-1:0] lessThanNextOutQueue;
  logic [QUEUE_SIZE-1:0] lessThanNextNextOutQueue;

  integer i, j;

  assign o_full   = next_size == QUEUE_SIZE;
  assign o_empty  = next_size == '0;

  assign o_node_f = outQueue[0];
  assign o_valid  = outQueueValid[0];

  always_comb begin
    // defaults
    next_size = curr_size;
    nextInQueue = '1;
    nextInQueueValid = '0;
    nextOutQueue = outQueue;
    nextOutQueueValid = outQueueValid;

    // push and pop operation control
    if (i_wrt && i_read) begin
      next_size = curr_size;
      if ((i_node_f < outQueue[0]) && (i_node_f < outQueue[1]) && (!inQueueValid[0] || (i_node_f < inQueue[0]))) begin
        // enqueue directly into outQueue[0]
        nextOutQueue[0] = i_node_f;
        nextOutQueueValid[0] = 1;
      end else begin
        // enqueue into inQueue[0]
        nextInQueue[0] = i_node_f;
        nextInQueueValid[0] = 1;
        // dequeue outQueue[0]
        nextOutQueue[0] = '1;
        nextOutQueueValid[0] = 0;
      end
    end else if (i_wrt) begin
      next_size = curr_size + 1;
      if ((i_node_f < outQueue[0]) && (i_node_f < outQueue[1]) && (!inQueueValid[0] || (i_node_f < inQueue[0]))) begin
        // enqueue directly into outQueue[0]
        nextOutQueue[0] = i_node_f;
        nextOutQueueValid[0] = 1;
        // Bump outQueue[0] into inQueue[0]
        nextInQueue[0] = outQueue[0];
        nextInQueueValid[0] = outQueueValid[0];
      end else begin
        // enqueue into inQueue[0]
        nextInQueue[0] = i_node_f;
        nextInQueueValid[0] = 1;
      end
    end else if (i_read) begin
      next_size = curr_size - 1;
      nextOutQueue[0] = '1;
      nextOutQueueValid[0] = 0;
    end

    // Initialize the comparators
    lessThanPrevInQueue      = '0;
    lessThanNextInQueue      = '0;
    lessThanSameOutQueue     = '0;
    lessThanNextOutQueue     = '0;
    lessThanNextNextOutQueue = '0;

    // comparsion for each node in queue
    for (j = 0; j < QUEUE_SIZE; j += 1) begin
      lessThanPrevInQueue[j] = (j > 0) ? (inQueue[j] < inQueue[j-1] ) : !i_wrt || (inQueue[j] <= i_node_f);
      lessThanNextInQueue[j] = (j < QUEUE_SIZE - 1) ? (inQueue[j] < inQueue[j+1]) : 1;
      lessThanSameOutQueue[j] = (inQueue[j] < outQueue[j]);
      lessThanNextOutQueue[j] = (j < QUEUE_SIZE - 1) ? (inQueue[j] < outQueue[j+1]) : 1;
      lessThanNextNextOutQueue[j] = (j < QUEUE_SIZE - 2) ? (inQueue[j] < outQueue[j+2]) : 1;
    end

    // Perform sorting based on comaprator result
    for (j = 0; j < QUEUE_SIZE - 1; j += 1) begin
      if (lessThanSameOutQueue[j] && lessThanNextOutQueue[j] && lessThanPrevInQueue[j]) begin
        // Insert inQueue into empty outQueue slot
        nextOutQueue[j] = inQueue[j];
        nextOutQueueValid[j] = inQueueValid[j];
      end else if (lessThanNextOutQueue[j] && lessThanNextInQueue[j] && lessThanNextNextOutQueue[j]) begin
        // Swap inQueue and outQueue
        nextInQueue[j+1] = outQueue[j+1];
        nextInQueueValid[j+1] = outQueueValid[j+1];
        nextOutQueue[j+1] = inQueue[j];
        nextOutQueueValid[j+1] = inQueueValid[j];
      end else if ((j == QUEUE_SIZE - 2) && !outQueueValid[j+1] && inQueueValid[j+1]) begin
        nextOutQueue[j+1] = inQueue[j+1];
        nextOutQueueValid[j+1] = inQueueValid[j+1];
      end else begin
        // Shift inQueue down
        nextInQueue[j+1] = inQueue[j];
        nextInQueueValid[j+1] = inQueueValid[j];
      end
    end

    // Shift outQueue length forward if there is a gap
    for (j = 0; j < QUEUE_SIZE - 1; j += 1) begin
      if (!outQueueValid[j] && !nextOutQueueValid[j]) begin
        nextOutQueue[j] = outQueue[j+1];
        nextOutQueueValid[j] = outQueueValid[j+1];
        nextOutQueue[j+1] = '1;
        nextOutQueueValid[j+1] = 0;
      end
    end
  end

  //========================================================================
  // ready logic
  //========================================================================

  typedef enum {
    STATE1,
    STATE2
  } State;
  State curr_state;
  State next_state;

  always_comb begin

    case (curr_state)

      STATE1: begin
        o_ready_deq = 1;
        o_ready_enq = 1;
        o_ready_rep = 1;
        if ((i_read && !i_wrt) || (i_read && i_wrt)) begin
          next_state = STATE2;
        end else begin
          next_state = STATE1;
        end
      end

      STATE2: begin
        o_ready_deq = 0;
        o_ready_enq = 1;
        o_ready_rep = 0;
        next_state  = STATE1;
      end

      default: begin
        o_ready_deq = 0;
        o_ready_enq = 0;
        o_ready_rep = 0;
        next_state  = STATE1;
      end

    endcase

  end

  always_ff @(posedge CLK) begin

    if (!RSTn) begin
      curr_size <= '0;
      curr_state <= STATE1;
      inQueueValid <= '0;
      outQueueValid <= '0;

      for (i = 0; i < QUEUE_SIZE; i += 1) begin
        inQueue[i]  <= '1;
        outQueue[i] <= '1;
      end

    end else begin
      curr_size     <= next_size;
      curr_state    <= next_state;
      inQueue       <= nextInQueue;
      inQueueValid  <= nextInQueueValid;
      outQueue      <= nextOutQueue;
      outQueueValid <= nextOutQueueValid;
    end

  end

endmodule

tb_open_list_queue.sv
/* verilator lint_off UNUSEDSIGNAL */

`timescale 1ns / 1ps
`define CLK_PERIOD 10

module tb_open_list_queue ();

  localparam QUEUE_SIZE = 4;
  localparam DATA_WIDTH = 32;
  localparam MAP_WIDTH = 16;
  localparam MAP_HEIGHT = 16;

  logic                  CLK;
  logic                  RSTn;

  /* control signals */
  logic                  i_wrt;  // enqueue
  logic                  i_read;  // dequeue
  logic                  i_valid;  // ready for next instruction
  logic [DATA_WIDTH-1:0] i_node_f;

  /* Output control signals */
  logic                  o_ready_deq;  // read ready flag
  logic                  o_ready_enq;  // write ready flag
  logic                  o_ready_rep;  // replace ready flag
  logic                  o_full;
  logic                  o_empty;
  logic                  o_valid;
  logic [DATA_WIDTH-1:0] o_node_f;

  open_list_queue #(QUEUE_SIZE, DATA_WIDTH, MAP_WIDTH, MAP_HEIGHT) u_open_list_queue (
      .CLK(CLK),
      .RSTn(RSTn),
      .i_wrt(i_wrt),
      .i_read(i_read),
      .i_valid(i_valid),
      .i_node_f(i_node_f),
      .o_ready_enq(o_ready_deq),
      .o_ready_deq(o_ready_enq),
      .o_ready_rep(o_ready_rep),
      .o_full(o_full),
      .o_empty(o_empty),
      .o_valid(o_valid),
      .o_node_f(o_node_f)
  );

  initial begin : CLK_GENERATION
    CLK = 0;
    forever #(`CLK_PERIOD / 2) CLK = !CLK;
  end

  initial begin : RST_GENERATION
    RSTn = 1;
    #1 RSTn = 0;
    repeat (2) @(negedge CLK);
    RSTn = 1;
  end

  initial begin : TEST

    $dumpfile("tb_open_list_queue.vcd");
    $dumpvars(0, tb_open_list_queue);

    i_wrt = 0;
    i_read = 0;
    i_valid = 0;
    i_node_f = 0;

    @(posedge RSTn);
    @(posedge CLK);

    // Enqueue operations
    write(5);
    write(2);
    write(3);
    write(7);

    // Dequeue operations and validate order
    read_and_check(2);
    read_and_check(3);
    read_and_check(5);
    read_and_check(7);

    $finish();
  end

  task write(input int i_data_f);
    if (o_full) $display("Write data: %d | Warning - The queue is full", i_data_f);
    else $display("Write data: %d", i_data_f);

    i_wrt = 1;
    i_node_f = i_data_f;
    i_valid = 1;

    @(posedge CLK);

    i_wrt = 0;

  endtask

  task read_and_check(input int expected_f);
    i_read = 1;

    if (o_valid) begin
      $display("Read data: %d", o_node_f);
      assert (o_node_f == expected_f)
      else $fatal("Assertion failed: Expected %d, got %d", expected_f, o_node_f);
    end else begin
      $display("Error - The queue is empty");
      assert (0)
      else $fatal("Assertion failed: Expected %d, but queue was empty", expected_f);
    end

    repeat (2) @(posedge CLK);
    i_read = 0;

  endtask

endmodule

tb_open_list_queue.vcd
$version Generated by VerilatedVcd $end
$timescale 1ps $end
 $scope module TOP $end
  $scope module tb_open_list_queue $end
   $var wire 32 M QUEUE_SIZE [31:0] $end
   $var wire 32 N DATA_WIDTH [31:0] $end
   $var wire 32 O MAP_WIDTH [31:0] $end
   $var wire 32 O MAP_HEIGHT [31:0] $end
   $var wire 1 ? CLK $end
   $var wire 1 @ RSTn $end
   $var wire 1 A i_wrt $end
   $var wire 1 B i_read $end
   $var wire 1 C i_valid $end
   $var wire 32 D i_node_f [31:0] $end
   $var wire 1 : o_ready_deq $end
   $var wire 1 ; o_ready_enq $end
   $var wire 1 < o_ready_rep $end
   $var wire 1 E o_full $end
   $var wire 1 F o_empty $end
   $var wire 1 G o_valid $end
   $var wire 32 6 o_node_f [31:0] $end
   $scope module u_open_list_queue $end
    $var wire 32 M QUEUE_SIZE [31:0] $end
    $var wire 32 N DATA_WIDTH [31:0] $end
    $var wire 32 O MAP_WIDTH [31:0] $end
    $var wire 32 O MAP_HEIGHT [31:0] $end
    $var wire 32 P MAX_F [31:0] $end
    $var wire 1 ? CLK $end
    $var wire 1 @ RSTn $end
    $var wire 1 A i_wrt $end
    $var wire 1 B i_read $end
    $var wire 1 C i_valid $end
    $var wire 32 D i_node_f [31:0] $end
    $var wire 1 ; o_ready_deq $end
    $var wire 1 : o_ready_enq $end
    $var wire 1 < o_ready_rep $end
    $var wire 1 E o_full $end
    $var wire 1 F o_empty $end
    $var wire 1 G o_valid $end
    $var wire 32 6 o_node_f [31:0] $end
    $var wire 32 Q l_bits [31:0] $end
    $var wire 4 H next_size [3:0] $end
    $var wire 4 I curr_size [3:0] $end
    $var wire 32 2 inQueue[0] [31:0] $end
    $var wire 32 3 inQueue[1] [31:0] $end
    $var wire 32 4 inQueue[2] [31:0] $end
    $var wire 32 5 inQueue[3] [31:0] $end
    $var wire 32 # nextInQueue[0] [31:0] $end
    $var wire 32 $ nextInQueue[1] [31:0] $end
    $var wire 32 % nextInQueue[2] [31:0] $end
    $var wire 32 & nextInQueue[3] [31:0] $end
    $var wire 32 6 outQueue[0] [31:0] $end
    $var wire 32 7 outQueue[1] [31:0] $end
    $var wire 32 8 outQueue[2] [31:0] $end
    $var wire 32 9 outQueue[3] [31:0] $end
    $var wire 32 ' nextOutQueue[0] [31:0] $end
    $var wire 32 ( nextOutQueue[1] [31:0] $end
    $var wire 32 ) nextOutQueue[2] [31:0] $end
    $var wire 32 * nextOutQueue[3] [31:0] $end
    $var wire 4 J inQueueValid [3:0] $end
    $var wire 4 + nextInQueueValid [3:0] $end
    $var wire 4 K outQueueValid [3:0] $end
    $var wire 4 , nextOutQueueValid [3:0] $end
    $var wire 4 - lessThanPrevInQueue [3:0] $end
    $var wire 4 . lessThanNextInQueue [3:0] $end
    $var wire 4 / lessThanSameOutQueue [3:0] $end
    $var wire 4 0 lessThanNextOutQueue [3:0] $end
    $var wire 4 1 lessThanNextNextOutQueue [3:0] $end
    $var wire 32 = i [31:0] $end
    $var wire 32 R j [31:0] $end
    $var wire 32 > curr_state [31:0] $end
    $var wire 32 L next_state [31:0] $end
   $upscope $end
  $upscope $end
 $upscope $end
$enddefinitions $end


#0
b11111111111111111111111111111111 #
b00000000000000000000000000000000 $
b00000000000000000000000000000000 %
b00000000000000000000000000000000 &
b00000000000000000000000000000000 '
b00000000000000000000000000000000 (
b00000000000000000000000000000000 )
b11111111111111111111111111111111 *
b0000 +
b0000 ,
b0001 -
b1000 .
b0000 /
b1000 0
b1100 1
b00000000000000000000000000000000 2
b00000000000000000000000000000000 3
b00000000000000000000000000000000 4
b00000000000000000000000000000000 5
b00000000000000000000000000000000 6
b00000000000000000000000000000000 7
b00000000000000000000000000000000 8
b00000000000000000000000000000000 9
1:
1;
1<
b00000000000000000000000000000000 =
b00000000000000000000000000000000 >
0?
1@
0A
0B
0C
b00000000000000000000000000000000 D
0E
1F
0G
b0000 H
b0000 I
b0000 J
b0000 K
b00000000000000000000000000000000 L
b00000000000000000000000000000100 M
b00000000000000000000000000100000 N
b00000000000000000000000000010000 O
b11111111111111111111111111111111 P
b00000000000000000000000000000010 Q
b00000000000000000000000000000011 R
#1000
0@
#5000
b11111111111111111111111111111111 $
b11111111111111111111111111111111 %
b11111111111111111111111111111111 &
b11111111111111111111111111111111 '
b11111111111111111111111111111111 (
b11111111111111111111111111111111 )
b11111111111111111111111111111111 2
b11111111111111111111111111111111 3
b11111111111111111111111111111111 4
b11111111111111111111111111111111 5
b11111111111111111111111111111111 6
b11111111111111111111111111111111 7
b11111111111111111111111111111111 8
b11111111111111111111111111111111 9
b00000000000000000000000000000100 =
1?
#10000
0?
#15000
1?
#20000
0?
1@
#25000
b00000000000000000000000000000101 #
b00000000000000000000000000000101 '
b0001 +
b0001 ,
b0000 -
b00000000000000000000000000000101 6
1?
1A
1C
b00000000000000000000000000000101 D
0F
1G
b0010 H
b0001 I
b0001 K
#30000
0?
#35000
b00000000000000000000000000000010 #
b00000000000000000000000000000010 '
b00000000000000000000000000000101 (
b0011 ,
b1001 .
b1001 0
b1101 1
b00000000000000000000000000000101 2
b00000000000000000000000000000010 6
1?
b00000000000000000000000000000010 D
b0011 H
b0010 I
b0001 J
#40000
0?
#45000
b00000000000000000000000000000011 #
b00000000000000000000000000000101 $
b00000000000000000000000000000011 (
b0011 +
b0001 -
b00000000000000000000000000000011 2
b00000000000000000000000000000101 7
1?
b00000000000000000000000000000011 D
1E
b0100 H
b0011 I
b0011 K
#50000
0?
#55000
b00000000000000000000000000000111 #
b00000000000000000000000000000111 $
b00000000000000000000000000000101 )
b0111 ,
b0011 -
b1010 .
b1010 0
b1111 1
b00000000000000000000000000000111 2
b00000000000000000000000000000101 3
b00000000000000000000000000000011 7
1?
b00000000000000000000000000000111 D
0E
b0101 H
b0100 I
b0011 J
#60000
0?
#65000
b11111111111111111111111111111111 #
b11111111111111111111111111111111 $
b00000000000000000000000000000111 %
b00000000000000000000000000000011 '
b11111111111111111111111111111111 (
b0100 +
b0101 ,
b1000 0
b1110 1
b11111111111111111111111111111111 2
b00000000000000000000000000000111 3
b11111111111111111111111111111111 6
b00000000000000000000000000000101 8
0;
0<
b00000000000000000000000000000001 >
1?
0A
1B
0G
b0010 H
b0011 I
b0010 J
b0110 K
#70000
0?
#75000
b11111111111111111111111111111111 %
b11111111111111111111111111111111 '
b00000000000000000000000000000101 (
b11111111111111111111111111111111 )
b00000000000000000000000000000111 *
b0000 +
b1010 ,
b0101 -
b1100 .
b1100 0
b1100 1
b11111111111111111111111111111111 3
b00000000000000000000000000000111 4
b00000000000000000000000000000011 6
b11111111111111111111111111111111 7
1;
1<
b00000000000000000000000000000000 >
1?
1G
b0001 H
b0010 I
b0100 J
b0101 K
b00000000000000000000000000000001 L
#80000
0?
#85000
b00000000000000000000000000000101 '
b11111111111111111111111111111111 (
b00000000000000000000000000000111 )
b11111111111111111111111111111111 *
b0101 ,
b0001 -
b1000 .
b1000 0
b11111111111111111111111111111111 4
b11111111111111111111111111111111 6
b00000000000000000000000000000101 7
b11111111111111111111111111111111 8
b00000000000000000000000000000111 9
0;
0<
b00000000000000000000000000000001 >
1?
1F
0G
b0000 H
b0001 I
b0000 J
b1010 K
b00000000000000000000000000000000 L
#90000
0?
#95000
b11111111111111111111111111111111 '
b00000000000000000000000000000111 (
b11111111111111111111111111111111 )
b0010 ,
b00000000000000000000000000000101 6
b11111111111111111111111111111111 7
b00000000000000000000000000000111 8
b11111111111111111111111111111111 9
1;
1<
b00000000000000000000000000000000 >
1?
0F
1G
b1111 H
b0000 I
b0101 K
b00000000000000000000000000000001 L
#100000
0?
#105000
b00000000000000000000000000000111 '
b11111111111111111111111111111111 (
b0001 ,
b11111111111111111111111111111111 6
b00000000000000000000000000000111 7
b11111111111111111111111111111111 8
0;
0<
b00000000000000000000000000000001 >
1?
0G
b1110 H
b1111 I
b0010 K
b00000000000000000000000000000000 L
#110000
0?
#115000
b11111111111111111111111111111111 '
b0000 ,
b00000000000000000000000000000111 6
b11111111111111111111111111111111 7
1;
1<
b00000000000000000000000000000000 >
1?
1G
b1101 H
b1110 I
b0001 K
b00000000000000000000000000000001 L
#120000
0?
#125000
b11111111111111111111111111111111 6
0;
0<
b00000000000000000000000000000001 >
1?
0G
b1100 H
b1101 I
b0000 K
b00000000000000000000000000000000 L
#130000
0?
#135000
1;
1<
b00000000000000000000000000000000 >
1?
b1011 H
b1100 I
b00000000000000000000000000000001 L
#140000
0?
#145000
1?
0B
b1100 H
b00000000000000000000000000000000 L
